LICENSE
README.rst
setup.py
ClassroomPrograms/__init__.py
ClassroomPrograms/pythonclass.py
ClassroomPrograms.egg-info/PKG-INFO
ClassroomPrograms.egg-info/SOURCES.txt
ClassroomPrograms.egg-info/dependency_links.txt
ClassroomPrograms.egg-info/requires.txt
ClassroomPrograms.egg-info/top_level.txt