Metadata-Version: 2.1
Name: ClassroomPrograms
Version: 1.0.0
Summary: Tool to support work in the classroom.
Home-page: https://github.com/josorio398/Classroom_Programs
Author: Jhonny Osorio Gallego
Author-email: osoriojohnny1986@gmail.com
License: CC BY-NC-SA 4.0
Download-URL: https://github.com/josorio398/Classroom_Programs/blob/main/pythonclass.py
Keywords: classroomprograms,classroom,programs,class lists,send mail,mass mailing
Platform: UNKNOWN
Classifier: Development Status :: 4 - Beta
Classifier: Intended Audience :: Developers
Classifier: Topic :: Software Development :: Build Tools
Classifier: Programming Language :: Python :: 3.4
Classifier: Programming Language :: Python :: 3.5
Classifier: Programming Language :: Python :: 3.6
Classifier: Programming Language :: Python :: 3.7
Classifier: Programming Language :: Python :: 3.8
Classifier: Programming Language :: Python :: 3.9
License-File: LICENSE
